docker_prune_plan/__init__.py
docker_prune_plan/cli.py
docker_prune_plan-0.2.1.dist-info/METADATA
docker_prune_plan-0.2.1.dist-info/WHEEL
docker_prune_plan-0.2.1.dist-info/entry_points.txt
docker_prune_plan-0.2.1.dist-info/top_level.txt
docker_prune_plan-0.2.1.dist-info/RECORD
