Metadata-Version: 2.4
Name: docker-prune-plan
Version: 0.2.1
Summary: Dry-run view of what docker prune commands would delete
Author-email: Abdul Wahab <abdulwahabmangat@gmail.com>
License: MIT
Project-URL: Homepage, https://github.com/wahabmangat/docker-prune-plan
Project-URL: Repository, https://github.com/wahabmangat/docker-prune-plan
Project-URL: Issues, https://github.com/wahabmangat/docker-prune-plan/issues
Project-URL: Changelog, https://github.com/wahabmangat/docker-prune-plan/blob/main/CHANGELOG.md
Keywords: docker,prune,cleanup,cli,dry-run
Classifier: Environment :: Console
Classifier: Intended Audience :: Developers
Classifier: Operating System :: OS Independent
Classifier: Programming Language :: Python :: 3
Classifier: Topic :: System :: Systems Administration
Classifier: Topic :: Utilities
Requires-Python: >=3.8
Requires-Dist: docker>=7.0.0
